LICENSE
MANIFEST.in
README.md
setup.cfg
setup.py
versioneer.py
python/kabaret/__init__.py
python/kabaret.subprocess_manager.egg-info/PKG-INFO
python/kabaret.subprocess_manager.egg-info/SOURCES.txt
python/kabaret.subprocess_manager.egg-info/dependency_links.txt
python/kabaret.subprocess_manager.egg-info/requires.txt
python/kabaret.subprocess_manager.egg-info/top_level.txt
python/kabaret/subprocess_manager/__init__.py
python/kabaret/subprocess_manager/_version.py
python/kabaret/subprocess_manager/runner_factory.py
python/kabaret/subprocess_manager/runners.py
python/kabaret/subprocess_manager/actor/__init__.py
python/kabaret/subprocess_manager/flow/__init__.py
python/kabaret/subprocess_manager/views/__init__.py
python/kabaret/subprocess_manager/views/launcher_toolbar.py
python/kabaret/subprocess_manager/views/subprocess_view.py