Metadata-Version: 2.4
Name: kabaret.subprocess_manager
Version: 1.3.0
Summary: Subprocess Management extension for the Kabaret framework
Home-page: https://gitlab.com/kabaretstudio/kabaret.subprocess_manager
Author: Damien "dee" Coureau
Author-email: kabaret-dev@googlegroups.com
License: LGPLv3+
Keywords: kabaret vfx animation pipeline dataflow workflow subprocess
Classifier: Development Status :: 4 - Beta
Classifier: Topic :: System :: Shells
Classifier: Intended Audience :: Developers
Classifier: Operating System :: Microsoft :: Windows :: Windows 10
Classifier: Programming Language :: Python :: 3.7
Classifier: License :: OSI Approved :: GNU Lesser General Public License v3 or later (LGPLv3+)
Requires-Python: >=2.7,!=3.0.*,!=3.1.*,!=3.2.*
License-File: LICENSE
Requires-Dist: kabaret>=2.4.0rc4
Requires-Dist: timeago
Provides-Extra: dev
Requires-Dist: twine; extra == "dev"
Requires-Dist: flake8; extra == "dev"
Requires-Dist: black; extra == "dev"
Dynamic: author
Dynamic: author-email
Dynamic: classifier
Dynamic: description
Dynamic: description-content-type
Dynamic: home-page
Dynamic: keywords
Dynamic: license
Dynamic: license-file
Dynamic: provides-extra
Dynamic: requires-dist
Dynamic: requires-python
Dynamic: summary
